Metadata-Version: 2.1
Name: morsepy-ru
Version: 0.1
Summary: morse decriptor and encriptor from russian language
Home-page: UNKNOWN
Author-email: katetlk@mail.ru
License: UNKNOWN
Platform: UNKNOWN
